clashai/__init__.py
clashai-1.0.5.dist-info/METADATA
clashai-1.0.5.dist-info/WHEEL
clashai-1.0.5.dist-info/top_level.txt
clashai-1.0.5.dist-info/RECORD
