Metadata-Version: 2.1
Name: clashai
Version: 1.0.5
Summary: An API wrapper for the ClashAI API
Author: lndrdev, invalidsian
License: MIT
Project-URL: GitHub, https://github.com/clashai/clashai
Project-URL: Documentation, https://clashai.readthedocs.io
Keywords: clash-ai,clashai,api,clashapi,clashai,ai,gpt,llama,mixtral,gemini
Classifier: Development Status :: 4 - Beta
Classifier: License :: OSI Approved :: MIT License
Classifier: Intended Audience :: Developers
Classifier: Operating System :: OS Independent
Classifier: Programming Language :: Python :: 3.9
Classifier: Programming Language :: Python :: 3.10
Classifier: Programming Language :: Python :: 3.11
Classifier: Programming Language :: Python :: 3.12
Requires-Python: >=3.9
Requires-Dist: requests
